PPPForgivenessSDK/base_api.py
PPPForgivenessSDK/client.py
PPPForgivenessSDK/direct_forgiveness.py
PPPForgivenessSDK/document_types.py
PPPForgivenessSDK/eidl_validation.py
PPPForgivenessSDK/forgiveness.py
PPPForgivenessSDK/loan_documents.py
PPPForgivenessSDK/messages.py
PPPForgivenessSDK/origination.py
PPPForgivenessSDK/validation.py
PPPForgivenessSDK-1.4.dist-info/LICENSE
PPPForgivenessSDK-1.4.dist-info/METADATA
PPPForgivenessSDK-1.4.dist-info/WHEEL
PPPForgivenessSDK-1.4.dist-info/top_level.txt
PPPForgivenessSDK-1.4.dist-info/RECORD
