Metadata-Version: 2.1
Name: PPPForgivenessSDK
Version: 1.4
Summary: api support for Paycheck Protection Program Portal
Home-page: https://sandbox.ussbaforgiveness.com/
Author: 
Author-email: 
License: UNKNOWN
Platform: UNKNOWN
Requires-Python: >2.7,!=3.0.*, !=3.1.*, !=3.2.*, !=3.3.*
License-File: LICENSE
Requires-Dist: python-dateutil
Requires-Dist: requests
